[{"1": [-Infinity, 0], "9": [-Infinity, 0], "consequence": 1}, {"1": [0, 4], "5": [-Infinity, 0], "9": [-Infinity, 0], "consequence": 1}, {"1": [0, 4], "9": [-Infinity, 0], "12": [-Infinity, 0], "consequence": 1}, {"1": [-Infinity, 0], "5": [-Infinity, 0], "9": [-Infinity, 0], "consequence": 1}, {"5": [-Infinity, 0], "7": [-Infinity, 0], "12": [-Infinity, 0], "consequence": 1}, {"1": [-Infinity, 0], "6": [0, 4], "consequence": 1}, {"1": [-Infinity, 0], "4": [-Infinity, 0], "6": [-Infinity, 0], "consequence": 1}, {"1": [0, 4], "2": [0, 2], "3": [-Infinity, 0], "consequence": 1}, {"1": [0, 4], "6": [-Infinity, 0], "9": [-Infinity, 0], "consequence": 1}, {"1": [0, 4], "6": [0, 4], "9": [-Infinity, 0], "consequence": 1}, {"1": [0, 4], "5": [-Infinity, 0], "6": [-Infinity, 0], "consequence": 1}, {"1": [0, 4], "3": [-Infinity, 0], "6": [0, 4], "consequence": 1}, {"1": [-Infinity, 0], "7": [0.0, Infinity], "14": [0.0, Infinity], "consequence": 1}, {"1": [0, 4], "9": [-Infinity, 0], "18": [0.0, Infinity], "consequence": 1}, {"0": [42, 66], "3": [-Infinity, 0], "consequence": 1}, {"0": [42, 66], "14": [0.0, Infinity], "18": [-Infinity, 0], "consequence": 1}, {"0": [42, 66], "6": [-Infinity, 0], "18": [-Infinity, 0], "consequence": 1}, {"1": [0, 4], "6": [6, 28], "9": [-Infinity, 0], "consequence": 1}, {"4": [-Infinity, 0], "6": [-Infinity, 0], "12": [-Infinity, 0], "consequence": 1}, {"1": [10, 16], "8": [-Infinity, 0], "12": [0.0, Infinity], "consequence": 0}, {"1": [0, 4], "7": [-Infinity, 0], "12": [-Infinity, 0], "consequence": 1}, {"1": [0, 4], "3": [-Infinity, 0], "18": [0.0, Infinity], "consequence": 1}, {"1": [15.0, Infinity], "7": [0.0, Infinity], "consequence": 0}, {"1": [15.0, Infinity], "5": [0.0, Infinity], "12": [0.0, Infinity], "consequence": 0}, {"1": [0, 4], "6": [0, 4], "10": [0.0, Infinity], "consequence": 1}, {"1": [0, 4], "2": [6, 26], "5": [-Infinity, 0], "consequence": 1}, {"0": [42, 66], "1": [4, 6], "consequence": 1}, {"1": [4, 6], "9": [-Infinity, 0], "12": [-Infinity, 0], "consequence": 1}, {"0": [20, 34], "1": [10, 16], "2": [0, 2], "consequence": 0}, {"1": [0, 4], "6": [28, 44], "9": [-Infinity, 0], "consequence": 1}, {"1": [0, 4], "2": [0, 2], "6": [-Infinity, 0], "consequence": 1}, {"0": [34, 38], "6": [0, 4], "12": [-Infinity, 0], "consequence": 1}, {"2": [0, 2], "7": [-Infinity, 0], "12": [-Infinity, 0], "consequence": 1}, {"1": [0, 4], "2": [0, 2], "6": [0, 4], "consequence": 1}, {"0": [42, 66], "1": [6, 8], "consequence": 1}, {"2": [6, 26], "3": [-Infinity, 0], "7": [-Infinity, 0], "consequence": 1}, {"1": [4, 6], "5": [-Infinity, 0], "9": [-Infinity, 0], "consequence": 1}, {"6": [-Infinity, 0], "7": [-Infinity, 0], "18": [-Infinity, 0], "consequence": 1}, {"1": [4, 6], "6": [-Infinity, 0], "18": [-Infinity, 0], "consequence": 1}, {"5": [0.0, Infinity], "6": [44, 349], "9": [0.0, Infinity], "consequence": 0}, {"0": [42, 66], "1": [8, 10], "4": [-Infinity, 0], "consequence": 1}, {"1": [4, 6], "6": [0, 4], "18": [-Infinity, 0], "consequence": 1}, {"0": [20, 34], "1": [8, 10], "5": [0.0, Infinity], "consequence": 0}, {"0": [42, 66], "1": [10, 16], "12": [-Infinity, 0], "consequence": 1}, {"1": [0, 4], "2": [-Infinity, 0], "10": [0.0, Infinity], "consequence": 1}, {"6": [44, 349], "9": [0.0, Infinity], "12": [0.0, Infinity], "consequence": 0}, {"1": [15.0, Infinity], "3": [0.0, Infinity], "18": [0.0, Infinity], "consequence": 0}, {"1": [6, 8], "5": [-Infinity, 0], "18": [-Infinity, 0], "consequence": 1}, {"2": [26, 750], "6": [0, 4], "14": [0.0, Infinity], "consequence": 1}, {"1": [0, 4], "2": [-Infinity, 0], "6": [0, 4], "consequence": 1}, {"4": [0.0, Infinity], "6": [-Infinity, 0], "10": [0.0, Infinity], "consequence": 1}, {"1": [6, 8], "6": [6, 28], "12": [-Infinity, 0], "consequence": 1}, {"1": [4, 6], "4": [-Infinity, 0], "7": [0.0, Infinity], "consequence": 1}, {"1": [8, 10], "5": [-Infinity, 0], "14": [0.0, Infinity], "consequence": 1}, {"1": [10, 16], "6": [0, 4], "8": [0.0, Infinity], "consequence": 1}, {"0": [42, 66], "4": [0.0, Infinity], "7": [-Infinity, 0], "consequence": 1}, {"1": [10, 16], "3": [0.0, Infinity], "8": [-Infinity, 0], "consequence": 0}, {"1": [4, 6], "5": [-Infinity, 0], "7": [-Infinity, 0], "consequence": 1}, {"1": [-Infinity, 0], "6": [4, 4], "7": [-Infinity, 0], "consequence": 1}, {"1": [4, 6], "4": [0.0, Infinity], "18": [-Infinity, 0], "consequence": 1}, {"1": [0, 4], "2": [-Infinity, 0], "6": [-Infinity, 0], "consequence": 1}, {"1": [0, 4], "2": [0, 2], "6": [6, 28], "consequence": 1}, {"1": [6, 8], "5": [-Infinity, 0], "7": [0.0, Infinity], "consequence": 1}, {"1": [4, 6], "6": [6, 28], "9": [0.0, Infinity], "consequence": 0}, {"6": [349.0, Infinity], "consequence": 0}, {"1": [4, 6], "4": [0.0, Infinity], "6": [0, 4], "consequence": 1}, {"1": [8, 10], "2": [0, 2], "3": [-Infinity, 0], "consequence": 1}, {"5": [0.0, Infinity], "6": [44, 349], "12": [0.0, Infinity], "consequence": 0}, {"0": [20, 34], "1": [6, 8], "4": [0.0, Infinity], "consequence": 0}, {"0": [38, 40], "1": [8, 10], "consequence": 1}, {"0": [20, 34], "1": [-Infinity, 0], "6": [6, 28], "consequence": 1}, {"1": [8, 10], "2": [26, 750], "6": [44, 349], "consequence": 1}, {"0": [42, 66], "1": [10, 16], "7": [-Infinity, 0], "consequence": 1}, {"1": [10, 16], "3": [0.0, Infinity], "6": [28, 44], "consequence": 0}, {"1": [6, 8], "6": [-Infinity, 0], "consequence": 1}, {"1": [0, 4], "6": [4, 6], "consequence": 1}, {"1": [8, 10], "5": [-Infinity, 0], "6": [0, 4], "consequence": 1}, {"0": [34, 38], "1": [8, 10], "2": [26, 750], "consequence": 1}, {"0": [18, 20], "1": [-Infinity, 0], "consequence": 1}, {"0": [34, 38], "1": [6, 8], "6": [6, 28], "consequence": 1}, {"1": [8, 10], "6": [0, 4], "14": [0.0, Infinity], "consequence": 1}, {"1": [10, 16], "6": [-Infinity, 0], "12": [0.0, Infinity], "consequence": 0}, {"1": [6, 8], "6": [6, 28], "consequence": 1}, {"1": [-Infinity, 0], "2": [26, 750], "6": [6, 28], "consequence": 1}, {"6": [44, 349], "14": [0.0, Infinity], "consequence": 1}, {"1": [6, 8], "6": [0, 4], "7": [0.0, Infinity], "consequence": 1}, {"2": [0, 2], "6": [28, 44], "9": [0.0, Infinity], "consequence": 0}, {"2": [26, 750], "4": [0.0, Infinity], "6": [0, 4], "consequence": 1}, {"1": [10, 16], "2": [26, 750], "12": [0.0, Infinity], "consequence": 0}, {"0": [34, 38], "1": [8, 10], "6": [0, 4], "consequence": 1}, {"1": [8, 10], "7": [0.0, Infinity], "14": [-Infinity, 0], "consequence": 0}, {"0": [34, 38], "1": [10, 16], "6": [4, 4], "consequence": 0}, {"0": [20, 34], "1": [6, 8], "12": [0.0, Infinity], "consequence": 0}, {"1": [4, 6], "4": [0.0, Infinity], "18": [0.0, Infinity], "consequence": 0}, {"6": [6, 28], "9": [0.0, Infinity], "10": [0.0, Infinity], "consequence": 0}, {"3": [0.0, Infinity], "9": [0.0, Infinity], "12": [0.0, Infinity], "consequence": 0}, {"0": [34, 38], "1": [6, 8], "6": [44, 349], "consequence": 0}, {"1": [4, 6], "5": [0.0, Infinity], "12": [0.0, Infinity], "consequence": 0}, {"1": [6, 8], "2": [-Infinity, 0], "14": [0.0, Infinity], "consequence": 0}, {"1": [4, 6], "3": [-Infinity, 0], "6": [44, 349], "consequence": 0}]